{
  "recipes": [
    {
      "id": "tiramisu",
      "name": "Tiramisù",
      "type": "dolce",
      "image": "https://via.placeholder.com/800x400",
      "difficulty": "Molto facile",
      "cost": "Molto economico",
      "preparation_time": "15 Minuti",
      "rest_time": "30 Minuti",
      "cooking_time": "15 Minuti",
      "servings": "6 porzioni",
      "cooking_method": "Fornello",
      "cuisine": "Italiana",
      "diet": "Onnivora",
      "histamine": false,
      "ingredients": [
        {"name": "Savoiardi", "quantity": "300g"},
        {"name": "Mascarpone", "quantity": "500g"},
        {"name": "Caffè", "quantity": "200ml"},
        {"name": "Cacao in polvere", "quantity": "q.b."}
      ],
      "instructions": "Iniziare preparando il caffè e lasciandolo raffreddare. Immergere i savoiardi nel caffè e alternarli con il mascarpone preparato..."
    },
    {
      "id": "cheesecake",
      "name": "Cheesecake",
      "type": "dolce",
      "image": "https://via.placeholder.com/800x400",
      "difficulty": "Facile",
      "cost": "Economico",
      "preparation_time": "20 Minuti",
      "rest_time": "2 Ore",
      "cooking_time": "No cottura",
      "servings": "8 porzioni",
      "cooking_method": "Frigo",
      "cuisine": "Americana",
      "diet": "Vegetariana",
      "histamine": false,
      "ingredients": [
        {"name": "Biscotti digestive", "quantity": "200g"},
        {"name": "Formaggio cremoso", "quantity": "400g"},
        {"name": "Zucchero", "quantity": "150g"},
        {"name": "Panna", "quantity": "200ml"}
      ],
      "instructions": "Per la base, tritare i biscotti e mescolarli con il burro fuso. Per la crema, mescolare il formaggio con lo zucchero e la panna..."
    },
    {
      "id": "pizza-margherita",
      "name": "Pizza Margherita",
      "type": "salato",
      "image": "https://via.placeholder.com/800x400",
      "difficulty": "Media",
      "cost": "Economico",
      "preparation_time": "30 Minuti",
      "rest_time": "1 Ora",
      "cooking_time": "20 Minuti",
      "servings": "4 porzioni",
      "cooking_method": "Forno",
      "cuisine": "Italiana",
      "diet": "Onnivora",
      "histamine": true,
      "ingredients": [
        {"name": "Farina", "quantity": "500g"},
        {"name": "Pomodoro", "quantity": "300g"},
        {"name": "Mozzarella", "quantity": "250g"},
        {"name": "Basilico", "quantity": "q.b."}
      ],
      "instructions": "Preparare l'impasto della pizza e lasciarlo lievitare. Condire con pomodoro, mozzarella e basilico, quindi cuocere in forno..."
    },
    {
      "id": "lasagna",
      "name": "Lasagna",
      "type": "salato",
      "image": "https://via.placeholder.com/800x400",
      "difficulty": "Media",
      "cost": "Economico",
      "preparation_time": "40 Minuti",
      "rest_time": "1 Ora",
      "cooking_time": "1 Ora",
      "servings": "6 porzioni",
      "cooking_method": "Forno",
      "cuisine": "Italiana",
      "diet": "Onnivora",
      "histamine": true,
      "ingredients": [
        {"name": "Pasta per lasagna", "quantity": "250g"},
        {"name": "Carne macinata", "quantity": "500g"},
        {"name": "Besciamella", "quantity": "500ml"},
        {"name": "Pomodoro", "quantity": "400g"}
      ],
      "instructions": "Preparare il ragù e la besciamella, quindi alternare strati di pasta, carne e besciamella. Cuocere in forno..."
    },
    {
      "id": "piadina-senza-strutto",
      "name": "Piadina senza strutto all’Olio di Oliva",
      "type": "salato",
      "image": "https://www.giallozafferano.it/images/ricette/14808_1.jpg",
      "difficulty": "Molto facile",
      "cost": "Molto economico",
      "preparation_time": "15 Minuti",
      "rest_time": "30 Minuti",
      "cooking_time": "15 Minuti",
      "servings": "6 Piadine",
      "cooking_method": "Fornello",
      "cuisine": "Italiana",
      "diet": "Vegetariana",
      "histamine": false,
      "ingredients": [
        {"name": "Farina 00", "quantity": "300g"},
        {"name": "Acqua", "quantity": "150ml"},
        {"name": "Olio extravergine d’oliva", "quantity": "30g"},
        {"name": "Sale fino", "quantity": "5g"}
      ],
      "instructions": [
        "Preparate l’impasto: impastare a mano, in ciotola o in planetaria. Unire la farina e l’acqua a filo, poco alla volta.",
        "Iniziare a impastare, poi aggiungere a filo l'olio di oliva e infine il sale, sempre impastando. Continuare fino a formare un panetto morbido e non appiccicoso.",
        "Dividere l’impasto in pezzetti quante piadine si vogliono fare. Consigliato un numero da 4 a 6 a seconda della dimensione della padella.",
        "Formare delle palline con l’impasto e coprirle con pellicola. Lasciarle riposare per 30 minuti su un piano leggermente infarinato.",
        "Stendere ciascun panetto formando un disco di spessore di massimo 3mm.",
        "Riscaldare una padella antiaderente e, quando è ben calda, adagiare la piadina. Cuocere per qualche minuto a fiamma bassa fino a quando si formano delle bollicine in superficie.",
        "Girare la piadina e cuocere l’altro lato fino a doratura.",
        "Continuare così con tutte le piadine e impilarle una sull’altra. Farcirle da calde o riscaldarle dopo."
      ]
    }
  ]
}
